{
  "teams": [
    {
      "name": "San Luis A",
      "pts": 2,
      "pj": 1,
      "g": 0,
      "e": 1,
      "p": 0,
      "pf": 0,
      "pc": 0,
      "bp": 0,
      "bf": 0,
      "form": [
        "d"
      ]
    },
    {
      "name": "Hurling A",
      "pts": 0,
      "pj": 0,
      "g": 0,
      "e": 0,
      "p": 0,
      "pf": 0,
      "pc": 0,
      "bp": 0,
      "bf": 0,
      "form": []
    },
    {
      "name": "Univ. De la Plata A",
      "pts": 0,
      "pj": 0,
      "g": 0,
      "e": 0,
      "p": 0,
      "pf": 0,
      "pc": 0,
      "bp": 0,
      "bf": 0,
      "form": []
    },
    {
      "name": "Lomas Athl. A",
      "pts": 0,
      "pj": 0,
      "g": 0,
      "e": 0,
      "p": 0,
      "pf": 0,
      "pc": 0,
      "bp": 0,
      "bf": 0,
      "form": []
    },
    {
      "name": "C.U de Quilmes A",
      "pts": 0,
      "pj": 0,
      "g": 0,
      "e": 0,
      "p": 0,
      "pf": 0,
      "pc": 0,
      "bp": 0,
      "bf": 0,
      "form": []
    },
    {
      "name": "Los Molinos A",
      "pts": 0,
      "pj": 0,
      "g": 0,
      "e": 0,
      "p": 0,
      "pf": 0,
      "pc": 0,
      "bp": 0,
      "bf": 0,
      "form": []
    },
    {
      "name": "Curupayti A",
      "pts": 0,
      "pj": 0,
      "g": 0,
      "e": 0,
      "p": 0,
      "pf": 0,
      "pc": 0,
      "bp": 0,
      "bf": 0,
      "form": []
    },
    {
      "name": "Del Sur A",
      "pts": 0,
      "pj": 0,
      "g": 0,
      "e": 0,
      "p": 0,
      "pf": 0,
      "pc": 0,
      "bp": 0,
      "bf": 0,
      "form": []
    },
    {
      "name": "El Retiro A",
      "pts": 0,
      "pj": 0,
      "g": 0,
      "e": 0,
      "p": 0,
      "pf": 0,
      "pc": 0,
      "bp": 0,
      "bf": 0,
      "form": []
    },
    {
      "name": "Bye",
      "pts": 2,
      "pj": 1,
      "g": 0,
      "e": 1,
      "p": 0,
      "pf": 0,
      "pc": 0,
      "bp": 0,
      "bf": 0,
      "form": [
        "d"
      ]
    },
    {
      "name": "A.D. Francesa A",
      "pts": 0,
      "pj": 0,
      "g": 0,
      "e": 0,
      "p": 0,
      "pf": 0,
      "pc": 0,
      "bp": 0,
      "bf": 0,
      "form": []
    },
    {
      "name": "San Fernando A",
      "pts": 0,
      "pj": 0,
      "g": 0,
      "e": 0,
      "p": 0,
      "pf": 0,
      "pc": 0,
      "bp": 0,
      "bf": 0,
      "form": []
    }
  ],
  "matches": {
    "1": {
      "date": "",
      "ms": [
        {
          "home": "San Fernando A",
          "away": "A.D. Francesa A",
          "played": false
        },
        {
          "home": "San Luis A",
          "away": "Bye",
          "played": true,
          "hs": 0,
          "as": 0
        },
        {
          "home": "Hurling A",
          "away": "El Retiro A",
          "played": false
        },
        {
          "home": "Univ. De la Plata A",
          "away": "Del Sur A",
          "played": false
        },
        {
          "home": "Lomas Athl. A",
          "away": "Curupayti A",
          "played": false
        },
        {
          "home": "C.U de Quilmes A",
          "away": "Los Molinos A",
          "played": false
        }
      ]
    },
    "2": {
      "date": "",
      "ms": [
        {
          "home": "C.U de Quilmes A",
          "away": "San Fernando A",
          "played": false
        },
        {
          "home": "Los Molinos A",
          "away": "Lomas Athl. A",
          "played": false
        },
        {
          "home": "Curupayti A",
          "away": "Univ. De la Plata A",
          "played": false
        },
        {
          "home": "Del Sur A",
          "away": "Hurling A",
          "played": false
        },
        {
          "home": "El Retiro A",
          "away": "San Luis A",
          "played": false
        },
        {
          "home": "Bye",
          "away": "A.D. Francesa A",
          "played": false
        }
      ]
    },
    "3": {
      "date": "",
      "ms": [
        {
          "home": "San Fernando A",
          "away": "Bye",
          "played": false
        },
        {
          "home": "A.D. Francesa A",
          "away": "El Retiro A",
          "played": false
        },
        {
          "home": "San Luis A",
          "away": "Del Sur A",
          "played": false
        },
        {
          "home": "Hurling A",
          "away": "Curupayti A",
          "played": false
        },
        {
          "home": "Univ. De la Plata A",
          "away": "Los Molinos A",
          "played": false
        },
        {
          "home": "Lomas Athl. A",
          "away": "C.U de Quilmes A",
          "played": false
        }
      ]
    },
    "4": {
      "date": "",
      "ms": [
        {
          "home": "Lomas Athl. A",
          "away": "San Fernando A",
          "played": false
        },
        {
          "home": "C.U de Quilmes A",
          "away": "Univ. De la Plata A",
          "played": false
        },
        {
          "home": "Los Molinos A",
          "away": "Hurling A",
          "played": false
        },
        {
          "home": "Curupayti A",
          "away": "San Luis A",
          "played": false
        },
        {
          "home": "Del Sur A",
          "away": "A.D. Francesa A",
          "played": false
        },
        {
          "home": "El Retiro A",
          "away": "Bye",
          "played": false
        }
      ]
    },
    "5": {
      "date": "",
      "ms": [
        {
          "home": "San Fernando A",
          "away": "El Retiro A",
          "played": false
        },
        {
          "home": "Bye",
          "away": "Del Sur A",
          "played": false
        },
        {
          "home": "A.D. Francesa A",
          "away": "Curupayti A",
          "played": false
        },
        {
          "home": "San Luis A",
          "away": "Los Molinos A",
          "played": false
        },
        {
          "home": "Hurling A",
          "away": "C.U de Quilmes A",
          "played": false
        },
        {
          "home": "Univ. De la Plata A",
          "away": "Lomas Athl. A",
          "played": false
        }
      ]
    },
    "6": {
      "date": "",
      "ms": [
        {
          "home": "Univ. De la Plata A",
          "away": "San Fernando A",
          "played": false
        },
        {
          "home": "Lomas Athl. A",
          "away": "Hurling A",
          "played": false
        },
        {
          "home": "C.U de Quilmes A",
          "away": "San Luis A",
          "played": false
        },
        {
          "home": "Los Molinos A",
          "away": "A.D. Francesa A",
          "played": false
        },
        {
          "home": "Curupayti A",
          "away": "Bye",
          "played": false
        },
        {
          "home": "Del Sur A",
          "away": "El Retiro A",
          "played": false
        }
      ]
    },
    "7": {
      "date": "",
      "ms": [
        {
          "home": "San Fernando A",
          "away": "Del Sur A",
          "played": false
        },
        {
          "home": "El Retiro A",
          "away": "Curupayti A",
          "played": false
        },
        {
          "home": "Bye",
          "away": "Los Molinos A",
          "played": false
        },
        {
          "home": "A.D. Francesa A",
          "away": "C.U de Quilmes A",
          "played": false
        },
        {
          "home": "San Luis A",
          "away": "Lomas Athl. A",
          "played": false
        },
        {
          "home": "Hurling A",
          "away": "Univ. De la Plata A",
          "played": false
        }
      ]
    },
    "8": {
      "date": "",
      "ms": [
        {
          "home": "Hurling A",
          "away": "San Fernando A",
          "played": false
        },
        {
          "home": "Univ. De la Plata A",
          "away": "San Luis A",
          "played": false
        },
        {
          "home": "Lomas Athl. A",
          "away": "A.D. Francesa A",
          "played": false
        },
        {
          "home": "C.U de Quilmes A",
          "away": "Bye",
          "played": false
        },
        {
          "home": "Los Molinos A",
          "away": "El Retiro A",
          "played": false
        },
        {
          "home": "Curupayti A",
          "away": "Del Sur A",
          "played": false
        }
      ]
    },
    "9": {
      "date": "",
      "ms": [
        {
          "home": "San Fernando A",
          "away": "Curupayti A",
          "played": false
        },
        {
          "home": "Del Sur A",
          "away": "Los Molinos A",
          "played": false
        },
        {
          "home": "El Retiro A",
          "away": "C.U de Quilmes A",
          "played": false
        },
        {
          "home": "Bye",
          "away": "Lomas Athl. A",
          "played": false
        },
        {
          "home": "A.D. Francesa A",
          "away": "Univ. De la Plata A",
          "played": false
        },
        {
          "home": "San Luis A",
          "away": "Hurling A",
          "played": false
        }
      ]
    },
    "10": {
      "date": "",
      "ms": [
        {
          "home": "San Luis A",
          "away": "San Fernando A",
          "played": false
        },
        {
          "home": "Hurling A",
          "away": "A.D. Francesa A",
          "played": false
        },
        {
          "home": "Univ. De la Plata A",
          "away": "Bye",
          "played": false
        },
        {
          "home": "Lomas Athl. A",
          "away": "El Retiro A",
          "played": false
        },
        {
          "home": "C.U de Quilmes A",
          "away": "Del Sur A",
          "played": false
        },
        {
          "home": "Los Molinos A",
          "away": "Curupayti A",
          "played": false
        }
      ]
    },
    "11": {
      "date": "",
      "ms": [
        {
          "home": "San Fernando A",
          "away": "Los Molinos A",
          "played": false
        },
        {
          "home": "Curupayti A",
          "away": "C.U de Quilmes A",
          "played": false
        },
        {
          "home": "Del Sur A",
          "away": "Lomas Athl. A",
          "played": false
        },
        {
          "home": "El Retiro A",
          "away": "Univ. De la Plata A",
          "played": false
        },
        {
          "home": "Bye",
          "away": "Hurling A",
          "played": false
        },
        {
          "home": "A.D. Francesa A",
          "away": "San Luis A",
          "played": false
        }
      ]
    }
  },
  "lastUpdate": "2026-04-12T15:10:14.474213+00:00",
  "matchesScraped": 1,
  "championshipId": "2025247",
  "nombre": "M16 G"
}