{
  "teams": [
    {
      "name": "Hurling",
      "pts": 15,
      "pj": 4,
      "g": 3,
      "e": 0,
      "p": 1,
      "pf": 145,
      "pc": 98,
      "bp": 3,
      "bf": 0,
      "form": [
        "w",
        "w",
        "l",
        "w"
      ]
    },
    {
      "name": "Lomas Athletic",
      "pts": 13,
      "pj": 4,
      "g": 3,
      "e": 0,
      "p": 1,
      "pf": 82,
      "pc": 92,
      "bp": 1,
      "bf": 0,
      "form": [
        "w",
        "l",
        "w",
        "w"
      ]
    },
    {
      "name": "Curupayti",
      "pts": 13,
      "pj": 4,
      "g": 3,
      "e": 0,
      "p": 1,
      "pf": 156,
      "pc": 128,
      "bp": 0,
      "bf": 1,
      "form": [
        "w",
        "w",
        "l",
        "w"
      ]
    },
    {
      "name": "San Luis",
      "pts": 10,
      "pj": 4,
      "g": 2,
      "e": 0,
      "p": 2,
      "pf": 146,
      "pc": 115,
      "bp": 1,
      "bf": 1,
      "form": [
        "w",
        "l",
        "w",
        "l"
      ]
    },
    {
      "name": "Olivos",
      "pts": 4,
      "pj": 4,
      "g": 1,
      "e": 0,
      "p": 3,
      "pf": 74,
      "pc": 136,
      "bp": 0,
      "bf": 0,
      "form": [
        "l",
        "w",
        "l",
        "l"
      ]
    },
    {
      "name": "Gimnasia y Esgrima",
      "pts": 16,
      "pj": 4,
      "g": 4,
      "e": 0,
      "p": 0,
      "pf": 120,
      "pc": 84,
      "bp": 0,
      "bf": 0,
      "form": [
        "w",
        "w",
        "w",
        "w"
      ]
    },
    {
      "name": "San Albano",
      "pts": 1,
      "pj": 4,
      "g": 0,
      "e": 0,
      "p": 4,
      "pf": 74,
      "pc": 145,
      "bp": 0,
      "bf": 1,
      "form": [
        "l",
        "l",
        "l",
        "l"
      ]
    },
    {
      "name": "San Cirano",
      "pts": 15,
      "pj": 4,
      "g": 3,
      "e": 0,
      "p": 1,
      "pf": 148,
      "pc": 102,
      "bp": 2,
      "bf": 1,
      "form": [
        "w",
        "w",
        "w",
        "l"
      ]
    },
    {
      "name": "Deportiva Francesa",
      "pts": 0,
      "pj": 4,
      "g": 0,
      "e": 0,
      "p": 4,
      "pf": 102,
      "pc": 163,
      "bp": 0,
      "bf": 0,
      "form": [
        "l",
        "l",
        "l",
        "l"
      ]
    },
    {
      "name": "San Fernando",
      "pts": 14,
      "pj": 4,
      "g": 3,
      "e": 0,
      "p": 1,
      "pf": 136,
      "pc": 70,
      "bp": 2,
      "bf": 0,
      "form": [
        "l",
        "w",
        "w",
        "w"
      ]
    },
    {
      "name": "Pueyrredon",
      "pts": 5,
      "pj": 4,
      "g": 1,
      "e": 0,
      "p": 3,
      "pf": 86,
      "pc": 124,
      "bp": 0,
      "bf": 1,
      "form": [
        "l",
        "l",
        "l",
        "w"
      ]
    },
    {
      "name": "Universitario de la Plata",
      "pts": 2,
      "pj": 4,
      "g": 0,
      "e": 0,
      "p": 4,
      "pf": 89,
      "pc": 124,
      "bp": 0,
      "bf": 2,
      "form": [
        "l",
        "l",
        "l",
        "l"
      ]
    },
    {
      "name": "San Andres",
      "pts": 9,
      "pj": 4,
      "g": 2,
      "e": 0,
      "p": 2,
      "pf": 84,
      "pc": 95,
      "bp": 0,
      "bf": 1,
      "form": [
        "l",
        "w",
        "w",
        "l"
      ]
    },
    {
      "name": "Pucara",
      "pts": 14,
      "pj": 4,
      "g": 3,
      "e": 0,
      "p": 1,
      "pf": 127,
      "pc": 93,
      "bp": 1,
      "bf": 1,
      "form": [
        "w",
        "l",
        "w",
        "w"
      ]
    }
  ],
  "matches": {
    "1": {
      "date": "",
      "ms": [
        {
          "home": "Pucara",
          "away": "San Andres",
          "played": true,
          "hs": 30,
          "as": 27,
          "bf_away": true
        },
        {
          "home": "Hurling",
          "away": "Universitario de la Plata",
          "played": true,
          "hs": 41,
          "as": 20,
          "bp_home": true
        },
        {
          "home": "Lomas Athletic",
          "away": "Pueyrredon",
          "played": true,
          "hs": 32,
          "as": 29,
          "bf_away": true
        },
        {
          "home": "Curupayti",
          "away": "San Fernando",
          "played": true,
          "hs": 36,
          "as": 27
        },
        {
          "home": "San Luis",
          "away": "Deportiva Francesa",
          "played": true,
          "hs": 39,
          "as": 31
        },
        {
          "home": "Olivos",
          "away": "San Cirano",
          "played": true,
          "hs": 22,
          "as": 45,
          "bp_away": true
        },
        {
          "home": "Gimnasia y Esgrima",
          "away": "San Albano",
          "played": true,
          "hs": 34,
          "as": 18
        }
      ]
    },
    "2": {
      "date": "",
      "ms": [
        {
          "home": "Gimnasia y Esgrima",
          "away": "Pucara",
          "played": true,
          "hs": 26,
          "as": 21,
          "bf_away": true
        },
        {
          "home": "San Albano",
          "away": "Olivos",
          "played": true,
          "hs": 15,
          "as": 17,
          "bf_home": true
        },
        {
          "home": "San Cirano",
          "away": "San Luis",
          "played": true,
          "hs": 45,
          "as": 25,
          "bp_home": true
        },
        {
          "home": "Deportiva Francesa",
          "away": "Curupayti",
          "played": true,
          "hs": 24,
          "as": 42
        },
        {
          "home": "San Fernando",
          "away": "Lomas Athletic",
          "played": true,
          "hs": 33,
          "as": 0,
          "bp_home": true
        },
        {
          "home": "Pueyrredon",
          "away": "Hurling",
          "played": true,
          "hs": 13,
          "as": 33,
          "bp_away": true
        },
        {
          "home": "Universitario de la Plata",
          "away": "San Andres",
          "played": true,
          "hs": 15,
          "as": 18,
          "bf_home": true
        }
      ]
    },
    "3": {
      "date": "",
      "ms": [
        {
          "home": "Pucara",
          "away": "Universitario de la Plata",
          "played": true,
          "hs": 31,
          "as": 23
        },
        {
          "home": "San Andres",
          "away": "Pueyrredon",
          "played": true,
          "hs": 28,
          "as": 10
        },
        {
          "home": "Hurling",
          "away": "San Fernando",
          "played": true,
          "hs": 23,
          "as": 36
        },
        {
          "home": "Lomas Athletic",
          "away": "Deportiva Francesa",
          "played": true,
          "hs": 34,
          "as": 18,
          "bp_home": true
        },
        {
          "home": "Curupayti",
          "away": "San Cirano",
          "played": true,
          "hs": 39,
          "as": 46,
          "bf_home": true
        },
        {
          "home": "San Luis",
          "away": "San Albano",
          "played": true,
          "hs": 55,
          "as": 10,
          "bp_home": true
        },
        {
          "home": "Olivos",
          "away": "Gimnasia y Esgrima",
          "played": true,
          "hs": 18,
          "as": 31
        }
      ]
    },
    "4": {
      "date": "",
      "ms": [
        {
          "home": "Olivos",
          "away": "Pucara",
          "played": true,
          "hs": 17,
          "as": 45,
          "bp_away": true
        },
        {
          "home": "Gimnasia y Esgrima",
          "away": "San Luis",
          "played": true,
          "hs": 29,
          "as": 27,
          "bf_away": true
        },
        {
          "home": "San Albano",
          "away": "Curupayti",
          "played": true,
          "hs": 31,
          "as": 39
        },
        {
          "home": "San Cirano",
          "away": "Lomas Athletic",
          "played": true,
          "hs": 12,
          "as": 16,
          "bf_home": true
        },
        {
          "home": "Deportiva Francesa",
          "away": "Hurling",
          "played": true,
          "hs": 29,
          "as": 48,
          "bp_away": true
        },
        {
          "home": "San Fernando",
          "away": "San Andres",
          "played": true,
          "hs": 40,
          "as": 11,
          "bp_home": true
        },
        {
          "home": "Pueyrredon",
          "away": "Universitario de la Plata",
          "played": true,
          "hs": 34,
          "as": 31,
          "bf_away": true
        }
      ]
    },
    "5": {
      "date": "",
      "ms": [
        {
          "home": "Pucara",
          "away": "Pueyrredon",
          "played": false
        },
        {
          "home": "Universitario de la Plata",
          "away": "San Fernando",
          "played": false
        },
        {
          "home": "San Andres",
          "away": "Deportiva Francesa",
          "played": false
        },
        {
          "home": "Hurling",
          "away": "San Cirano",
          "played": false
        },
        {
          "home": "Lomas Athletic",
          "away": "San Albano",
          "played": false
        },
        {
          "home": "Curupayti",
          "away": "Gimnasia y Esgrima",
          "played": false
        },
        {
          "home": "San Luis",
          "away": "Olivos",
          "played": false
        }
      ]
    },
    "6": {
      "date": "",
      "ms": [
        {
          "home": "San Luis",
          "away": "Pucara",
          "played": false
        },
        {
          "home": "Olivos",
          "away": "Curupayti",
          "played": false
        },
        {
          "home": "Gimnasia y Esgrima",
          "away": "Lomas Athletic",
          "played": false
        },
        {
          "home": "San Albano",
          "away": "Hurling",
          "played": false
        },
        {
          "home": "San Cirano",
          "away": "San Andres",
          "played": false
        },
        {
          "home": "Deportiva Francesa",
          "away": "Universitario de la Plata",
          "played": false
        },
        {
          "home": "San Fernando",
          "away": "Pueyrredon",
          "played": false
        }
      ]
    },
    "7": {
      "date": "",
      "ms": [
        {
          "home": "Pucara",
          "away": "San Fernando",
          "played": false
        },
        {
          "home": "Pueyrredon",
          "away": "Deportiva Francesa",
          "played": false
        },
        {
          "home": "Universitario de la Plata",
          "away": "San Cirano",
          "played": false
        },
        {
          "home": "San Andres",
          "away": "San Albano",
          "played": false
        },
        {
          "home": "Hurling",
          "away": "Gimnasia y Esgrima",
          "played": false
        },
        {
          "home": "Lomas Athletic",
          "away": "Olivos",
          "played": false
        },
        {
          "home": "Curupayti",
          "away": "San Luis",
          "played": false
        }
      ]
    },
    "8": {
      "date": "",
      "ms": [
        {
          "home": "Curupayti",
          "away": "Pucara",
          "played": false
        },
        {
          "home": "San Luis",
          "away": "Lomas Athletic",
          "played": false
        },
        {
          "home": "Olivos",
          "away": "Hurling",
          "played": false
        },
        {
          "home": "Gimnasia y Esgrima",
          "away": "San Andres",
          "played": false
        },
        {
          "home": "San Albano",
          "away": "Universitario de la Plata",
          "played": false
        },
        {
          "home": "San Cirano",
          "away": "Pueyrredon",
          "played": false
        },
        {
          "home": "Deportiva Francesa",
          "away": "San Fernando",
          "played": false
        }
      ]
    },
    "9": {
      "date": "",
      "ms": [
        {
          "home": "Pucara",
          "away": "Deportiva Francesa",
          "played": false
        },
        {
          "home": "San Fernando",
          "away": "San Cirano",
          "played": false
        },
        {
          "home": "Pueyrredon",
          "away": "San Albano",
          "played": false
        },
        {
          "home": "Universitario de la Plata",
          "away": "Gimnasia y Esgrima",
          "played": false
        },
        {
          "home": "San Andres",
          "away": "Olivos",
          "played": false
        },
        {
          "home": "Hurling",
          "away": "San Luis",
          "played": false
        },
        {
          "home": "Lomas Athletic",
          "away": "Curupayti",
          "played": false
        }
      ]
    },
    "10": {
      "date": "",
      "ms": [
        {
          "home": "Lomas Athletic",
          "away": "Pucara",
          "played": false
        },
        {
          "home": "Curupayti",
          "away": "Hurling",
          "played": false
        },
        {
          "home": "San Luis",
          "away": "San Andres",
          "played": false
        },
        {
          "home": "Olivos",
          "away": "Universitario de la Plata",
          "played": false
        },
        {
          "home": "Gimnasia y Esgrima",
          "away": "Pueyrredon",
          "played": false
        },
        {
          "home": "San Albano",
          "away": "San Fernando",
          "played": false
        },
        {
          "home": "San Cirano",
          "away": "Deportiva Francesa",
          "played": false
        }
      ]
    },
    "11": {
      "date": "",
      "ms": [
        {
          "home": "Pucara",
          "away": "San Cirano",
          "played": false
        },
        {
          "home": "Deportiva Francesa",
          "away": "San Albano",
          "played": false
        },
        {
          "home": "San Fernando",
          "away": "Gimnasia y Esgrima",
          "played": false
        },
        {
          "home": "Pueyrredon",
          "away": "Olivos",
          "played": false
        },
        {
          "home": "Universitario de la Plata",
          "away": "San Luis",
          "played": false
        },
        {
          "home": "San Andres",
          "away": "Curupayti",
          "played": false
        },
        {
          "home": "Hurling",
          "away": "Lomas Athletic",
          "played": false
        }
      ]
    },
    "12": {
      "date": "",
      "ms": [
        {
          "home": "Hurling",
          "away": "Pucara",
          "played": false
        },
        {
          "home": "Lomas Athletic",
          "away": "San Andres",
          "played": false
        },
        {
          "home": "Curupayti",
          "away": "Universitario de la Plata",
          "played": false
        },
        {
          "home": "San Luis",
          "away": "Pueyrredon",
          "played": false
        },
        {
          "home": "Olivos",
          "away": "San Fernando",
          "played": false
        },
        {
          "home": "Gimnasia y Esgrima",
          "away": "Deportiva Francesa",
          "played": false
        },
        {
          "home": "San Albano",
          "away": "San Cirano",
          "played": false
        }
      ]
    },
    "13": {
      "date": "",
      "ms": [
        {
          "home": "Pucara",
          "away": "San Albano",
          "played": false
        },
        {
          "home": "San Cirano",
          "away": "Gimnasia y Esgrima",
          "played": false
        },
        {
          "home": "Deportiva Francesa",
          "away": "Olivos",
          "played": false
        },
        {
          "home": "San Fernando",
          "away": "San Luis",
          "played": false
        },
        {
          "home": "Pueyrredon",
          "away": "Curupayti",
          "played": false
        },
        {
          "home": "Universitario de la Plata",
          "away": "Lomas Athletic",
          "played": false
        },
        {
          "home": "San Andres",
          "away": "Hurling",
          "played": false
        }
      ]
    },
    "14": {
      "date": "",
      "ms": [
        {
          "home": "San Andres",
          "away": "Pucara",
          "played": false
        },
        {
          "home": "Universitario de la Plata",
          "away": "Hurling",
          "played": false
        },
        {
          "home": "Pueyrredon",
          "away": "Lomas Athletic",
          "played": false
        },
        {
          "home": "San Fernando",
          "away": "Curupayti",
          "played": false
        },
        {
          "home": "Deportiva Francesa",
          "away": "San Luis",
          "played": false
        },
        {
          "home": "San Cirano",
          "away": "Olivos",
          "played": false
        },
        {
          "home": "San Albano",
          "away": "Gimnasia y Esgrima",
          "played": false
        }
      ]
    },
    "15": {
      "date": "",
      "ms": [
        {
          "home": "Pucara",
          "away": "Gimnasia y Esgrima",
          "played": false
        },
        {
          "home": "Olivos",
          "away": "San Albano",
          "played": false
        },
        {
          "home": "San Luis",
          "away": "San Cirano",
          "played": false
        },
        {
          "home": "Curupayti",
          "away": "Deportiva Francesa",
          "played": false
        },
        {
          "home": "Lomas Athletic",
          "away": "San Fernando",
          "played": false
        },
        {
          "home": "Hurling",
          "away": "Pueyrredon",
          "played": false
        },
        {
          "home": "San Andres",
          "away": "Universitario de la Plata",
          "played": false
        }
      ]
    },
    "16": {
      "date": "",
      "ms": [
        {
          "home": "Universitario de la Plata",
          "away": "Pucara",
          "played": false
        },
        {
          "home": "Pueyrredon",
          "away": "San Andres",
          "played": false
        },
        {
          "home": "San Fernando",
          "away": "Hurling",
          "played": false
        },
        {
          "home": "Deportiva Francesa",
          "away": "Lomas Athletic",
          "played": false
        },
        {
          "home": "San Cirano",
          "away": "Curupayti",
          "played": false
        },
        {
          "home": "San Albano",
          "away": "San Luis",
          "played": false
        },
        {
          "home": "Gimnasia y Esgrima",
          "away": "Olivos",
          "played": false
        }
      ]
    },
    "17": {
      "date": "",
      "ms": [
        {
          "home": "Pucara",
          "away": "Olivos",
          "played": false
        },
        {
          "home": "San Luis",
          "away": "Gimnasia y Esgrima",
          "played": false
        },
        {
          "home": "Curupayti",
          "away": "San Albano",
          "played": false
        },
        {
          "home": "Lomas Athletic",
          "away": "San Cirano",
          "played": false
        },
        {
          "home": "Hurling",
          "away": "Deportiva Francesa",
          "played": false
        },
        {
          "home": "San Andres",
          "away": "San Fernando",
          "played": false
        },
        {
          "home": "Universitario de la Plata",
          "away": "Pueyrredon",
          "played": false
        }
      ]
    },
    "18": {
      "date": "",
      "ms": [
        {
          "home": "Pueyrredon",
          "away": "Pucara",
          "played": false
        },
        {
          "home": "San Fernando",
          "away": "Universitario de la Plata",
          "played": false
        },
        {
          "home": "Deportiva Francesa",
          "away": "San Andres",
          "played": false
        },
        {
          "home": "San Cirano",
          "away": "Hurling",
          "played": false
        },
        {
          "home": "San Albano",
          "away": "Lomas Athletic",
          "played": false
        },
        {
          "home": "Gimnasia y Esgrima",
          "away": "Curupayti",
          "played": false
        },
        {
          "home": "Olivos",
          "away": "San Luis",
          "played": false
        }
      ]
    },
    "19": {
      "date": "",
      "ms": [
        {
          "home": "Pucara",
          "away": "San Luis",
          "played": false
        },
        {
          "home": "Curupayti",
          "away": "Olivos",
          "played": false
        },
        {
          "home": "Lomas Athletic",
          "away": "Gimnasia y Esgrima",
          "played": false
        },
        {
          "home": "Hurling",
          "away": "San Albano",
          "played": false
        },
        {
          "home": "San Andres",
          "away": "San Cirano",
          "played": false
        },
        {
          "home": "Universitario de la Plata",
          "away": "Deportiva Francesa",
          "played": false
        },
        {
          "home": "Pueyrredon",
          "away": "San Fernando",
          "played": false
        }
      ]
    },
    "20": {
      "date": "",
      "ms": [
        {
          "home": "San Fernando",
          "away": "Pucara",
          "played": false
        },
        {
          "home": "Deportiva Francesa",
          "away": "Pueyrredon",
          "played": false
        },
        {
          "home": "San Cirano",
          "away": "Universitario de la Plata",
          "played": false
        },
        {
          "home": "San Albano",
          "away": "San Andres",
          "played": false
        },
        {
          "home": "Gimnasia y Esgrima",
          "away": "Hurling",
          "played": false
        },
        {
          "home": "Olivos",
          "away": "Lomas Athletic",
          "played": false
        },
        {
          "home": "San Luis",
          "away": "Curupayti",
          "played": false
        }
      ]
    },
    "21": {
      "date": "",
      "ms": [
        {
          "home": "Pucara",
          "away": "Curupayti",
          "played": false
        },
        {
          "home": "Lomas Athletic",
          "away": "San Luis",
          "played": false
        },
        {
          "home": "Hurling",
          "away": "Olivos",
          "played": false
        },
        {
          "home": "San Andres",
          "away": "Gimnasia y Esgrima",
          "played": false
        },
        {
          "home": "Universitario de la Plata",
          "away": "San Albano",
          "played": false
        },
        {
          "home": "Pueyrredon",
          "away": "San Cirano",
          "played": false
        },
        {
          "home": "San Fernando",
          "away": "Deportiva Francesa",
          "played": false
        }
      ]
    },
    "22": {
      "date": "",
      "ms": [
        {
          "home": "Deportiva Francesa",
          "away": "Pucara",
          "played": false
        },
        {
          "home": "San Cirano",
          "away": "San Fernando",
          "played": false
        },
        {
          "home": "San Albano",
          "away": "Pueyrredon",
          "played": false
        },
        {
          "home": "Gimnasia y Esgrima",
          "away": "Universitario de la Plata",
          "played": false
        },
        {
          "home": "Olivos",
          "away": "San Andres",
          "played": false
        },
        {
          "home": "San Luis",
          "away": "Hurling",
          "played": false
        },
        {
          "home": "Curupayti",
          "away": "Lomas Athletic",
          "played": false
        }
      ]
    },
    "23": {
      "date": "",
      "ms": [
        {
          "home": "Pucara",
          "away": "Lomas Athletic",
          "played": false
        },
        {
          "home": "Hurling",
          "away": "Curupayti",
          "played": false
        },
        {
          "home": "San Andres",
          "away": "San Luis",
          "played": false
        },
        {
          "home": "Universitario de la Plata",
          "away": "Olivos",
          "played": false
        },
        {
          "home": "Pueyrredon",
          "away": "Gimnasia y Esgrima",
          "played": false
        },
        {
          "home": "San Fernando",
          "away": "San Albano",
          "played": false
        },
        {
          "home": "Deportiva Francesa",
          "away": "San Cirano",
          "played": false
        }
      ]
    },
    "24": {
      "date": "",
      "ms": [
        {
          "home": "San Cirano",
          "away": "Pucara",
          "played": false
        },
        {
          "home": "San Albano",
          "away": "Deportiva Francesa",
          "played": false
        },
        {
          "home": "Gimnasia y Esgrima",
          "away": "San Fernando",
          "played": false
        },
        {
          "home": "Olivos",
          "away": "Pueyrredon",
          "played": false
        },
        {
          "home": "San Luis",
          "away": "Universitario de la Plata",
          "played": false
        },
        {
          "home": "Curupayti",
          "away": "San Andres",
          "played": false
        },
        {
          "home": "Lomas Athletic",
          "away": "Hurling",
          "played": false
        }
      ]
    },
    "25": {
      "date": "",
      "ms": [
        {
          "home": "Pucara",
          "away": "Hurling",
          "played": false
        },
        {
          "home": "San Andres",
          "away": "Lomas Athletic",
          "played": false
        },
        {
          "home": "Universitario de la Plata",
          "away": "Curupayti",
          "played": false
        },
        {
          "home": "Pueyrredon",
          "away": "San Luis",
          "played": false
        },
        {
          "home": "San Fernando",
          "away": "Olivos",
          "played": false
        },
        {
          "home": "Deportiva Francesa",
          "away": "Gimnasia y Esgrima",
          "played": false
        },
        {
          "home": "San Cirano",
          "away": "San Albano",
          "played": false
        }
      ]
    },
    "26": {
      "date": "",
      "ms": [
        {
          "home": "San Albano",
          "away": "Pucara",
          "played": false
        },
        {
          "home": "Gimnasia y Esgrima",
          "away": "San Cirano",
          "played": false
        },
        {
          "home": "Olivos",
          "away": "Deportiva Francesa",
          "played": false
        },
        {
          "home": "San Luis",
          "away": "San Fernando",
          "played": false
        },
        {
          "home": "Curupayti",
          "away": "Pueyrredon",
          "played": false
        },
        {
          "home": "Lomas Athletic",
          "away": "Universitario de la Plata",
          "played": false
        },
        {
          "home": "Hurling",
          "away": "San Andres",
          "played": false
        }
      ]
    }
  },
  "lastUpdate": "2026-04-12T15:53:07.741319+00:00",
  "matchesScraped": 28,
  "championshipId": "2025177",
  "nombre": "Primera A"
}